memex_md_mcp/__init__.py
memex_md_mcp/__main__.py
memex_md_mcp/db.py
memex_md_mcp/embeddings.py
memex_md_mcp/indexer.py
memex_md_mcp/logging.py
memex_md_mcp/parser.py
memex_md_mcp/server.py
memex_md_mcp-1.2.0.dist-info/WHEEL
memex_md_mcp-1.2.0.dist-info/entry_points.txt
memex_md_mcp-1.2.0.dist-info/METADATA
memex_md_mcp-1.2.0.dist-info/RECORD
