Metadata-Version: 2.4
Name: memex-md-mcp
Version: 1.2.0
Summary: MCP server for semantic search over markdown vaults
Keywords: mcp,obsidian,markdown,semantic-search,embeddings,claude,agent,agentic,llm,rag
Author: Maximilian Wolf
License-Expression: MIT
Classifier: Development Status :: 3 - Alpha
Classifier: Intended Audience :: Developers
Classifier: License :: OSI Approved :: MIT License
Classifier: Programming Language :: Python :: 3
Classifier: Programming Language :: Python :: 3.14
Requires-Dist: mcp[cli]>=1.24.0
Requires-Dist: python-frontmatter>=1.1.0
Requires-Dist: sentence-transformers>=5.2.0
Requires-Dist: sqlite-vec>=0.1.6
Requires-Dist: pre-commit>=4.0.0 ; extra == 'dev'
Requires-Python: >=3.14
Project-URL: Issues, https://github.com/MaxWolf-01/memex/issues
Project-URL: Repository, https://github.com/MaxWolf-01/memex
Provides-Extra: dev
